rbx/__init__.py
rbx/exceptions.py
rbx/logging.py
rbx/settings.py
rbx/auth/__init__.py
rbx/auth/decorators.py
rbx/auth/id_token.py
rbx/auth/keystore.py
rbx/auth/mock.py
rbx/aws/__init__.py
rbx/aws/s3.py
rbx/buildtools/__init__.py
rbx/buildtools/cli.py
rbx/buildtools/tasks/__init__.py
rbx/buildtools/tasks/ec2.py
rbx/buildtools/tasks/image.py
rbx/buildtools/tasks/misc.py
rbx/clients/__init__.py
rbx/clients/adsquare.py
rbx/clients/broadsign.py
rbx/clients/oxr.py
rbx/clients/panels.py
rbx/clients/place_exchange.py
rbx/clients/reporting.py
rbx/clients/retry.py
rbx/gcp/__init__.py
rbx/gcp/cloud_tasks.py
rbx/gcp/pubsub.py
rbx/gcp/storage.py
rbx/utils/__init__.py
rbx/utils/mdm.py
rbx/utils/vast.py
rbx/web/__init__.py
rbx/web/handlers.py
rbx-3.24.0.dist-info/licenses/LICENSE
rbx-3.24.0.dist-info/METADATA
rbx-3.24.0.dist-info/WHEEL
rbx-3.24.0.dist-info/entry_points.txt
rbx-3.24.0.dist-info/top_level.txt
rbx-3.24.0.dist-info/RECORD
